{
    "boardwidth": 10,
    "boardheight": 8,
    "colourtomove": 1,
    "precedingmove": {
        "x_from": 2,
        "y_from": 6,
        "x_to": 2,
        "y_to": 4
      },
        "squares": [
        "  .|  .|  .|  .|  .|  .|-Dn|-Dn|  .|  .",
        "  .|-So|  .|  .|  .|  .|  .|  .|  .|  .",
        "  .|  .|  .|-So|  .|  .|  .|  .| -R|  .",
        "  .|  .|  .|  .|  .|  .|  .|  .|  .|  .",
        "  .|  .|  .|  .|  .|  .|  .|  .|  .|  .",
        "  .|  R|  .|  .|  .|  .| So|  .|  .|  .",
        "  .|  .|  .|  .|  .|  .|  .|  .| So|  .",
        "  .|  .| Dn| Dn|  .|  .|  .|  .|  .|  ."
    ],
    "terrain": [
        "  .|  .|  .|  .|  .|  .|  .|  .|  .|  .",
        "  .|  .|  .|  .|  .|  .|  .|  .|  .|  .",
        "  .|  .|  .|  .|  .|  .|  .|  .| h1|  .",
        "  .|  .|  .|  .|  .|  .|  .|  .|  .|  .",
        "  .|  .|  .|  .|  .|  .|  .|  .|  .|  .",
        "  .| h1|  .|  .|  .|  .|  .|  .|  .|  .",
        "  .|  .|  .|  .|  .|  .|  .|  .|  .|  .",
        "  .|  .|  .|  .|  .|  .|  .|  .|  .|  ."
    ]
}
